__init__.py
cedula_uruguaya.py
cedula_uruguaya-0.1.1.dist-info/METADATA
cedula_uruguaya-0.1.1.dist-info/WHEEL
cedula_uruguaya-0.1.1.dist-info/top_level.txt
cedula_uruguaya-0.1.1.dist-info/RECORD
