Metadata-Version: 2.1
Name: cedula_uruguaya
Version: 0.1.1
Summary: Gestión de cédulas uruguayas con validación de dígitos verificadores
Author-email: SoyVA3 <vic@knowmadinstitut.com>
License: MIT
Project-URL: Homepage, https://github.com/VicThor-wpp/cedula_uruguaya
Classifier: Programming Language :: Python :: 3
Classifier: License :: OSI Approved :: MIT License
Classifier: Operating System :: OS Independent
Requires-Python: >=3.8
Provides-Extra: test
Requires-Dist: pytest ; extra == 'test'
Requires-Dist: pytest-cov ; extra == 'test'
